{
"type": "FeatureCollection",
"crs": { "type": "name", "properties": { "name": "urn:ogc:def:crs:OGC:1.3:CRS84" } },
"features": [
{ "type": "Feature", "properties": { "DIRECCION": "Peaje de la Av. General Rumiñahui", "Codigo del cliente": "Peaje de la Av. General Rumiñahui" }, "geometry": { "type": "Point", "coordinates": [ -78.485332, -0.242651 ] } },
{ "type": "Feature", "properties": { "DIRECCION": "Peaje de la Av. General Rumiñahui", "Codigo del cliente": "Peaje de la Av. General Rumiñahui" }, "geometry": { "type": "Point", "coordinates": [ -78.485332, -0.242651 ] } },
{ "type": "Feature", "properties": { "DIRECCION": "Peaje de la Av. General Rumiñahui", "Codigo del cliente": "Peaje de la Av. General Rumiñahui" }, "geometry": { "type": "Point", "coordinates": [ -78.485332, -0.242651 ] } },
{ "type": "Feature", "properties": { "DIRECCION": "Peaje de la Av. General Rumiñahui", "Codigo del cliente": "Peaje de la Av. General Rumiñahui" }, "geometry": { "type": "Point", "coordinates": [ -78.485332, -0.242651 ] } },
{ "type": "Feature", "properties": { "DIRECCION": "Peaje de la Av. General Rumiñahui", "Codigo del cliente": "Peaje de la Av. General Rumiñahui" }, "geometry": { "type": "Point", "coordinates": [ -78.485332, -0.242651 ] } },
{ "type": "Feature", "properties": { "DIRECCION": "Peaje de la Av. General Rumiñahui", "Codigo del cliente": "Peaje de la Av. General Rumiñahui" }, "geometry": { "type": "Point", "coordinates": [ -78.485332, -0.242651 ] } },
{ "type": "Feature", "properties": { "DIRECCION": "Peaje de la Av. General Rumiñahui", "Codigo del cliente": "Peaje de la Av. General Rumiñahui" }, "geometry": { "type": "Point", "coordinates": [ -78.485332, -0.242651 ] } },
{ "type": "Feature", "properties": { "DIRECCION": "Peaje de la Av. General Rumiñahui", "Codigo del cliente": "Peaje de la Av. General Rumiñahui" }, "geometry": { "type": "Point", "coordinates": [ -78.485332, -0.242651 ] } },
{ "type": "Feature", "properties": { "DIRECCION": "Peaje de la Av. General Rumiñahui", "Codigo del cliente": "Peaje de la Av. General Rumiñahui" }, "geometry": { "type": "Point", "coordinates": [ -78.485332, -0.242651 ] } },
{ "type": "Feature", "properties": { "DIRECCION": "Peaje de la Av. General Rumiñahui", "Codigo del cliente": "Peaje de la Av. General Rumiñahui" }, "geometry": { "type": "Point", "coordinates": [ -78.485332, -0.242651 ] } },
{ "type": "Feature", "properties": { "DIRECCION": "Peaje de la Av. General Rumiñahui", "Codigo del cliente": "Peaje de la Av. General Rumiñahui" }, "geometry": { "type": "Point", "coordinates": [ -78.485332, -0.242651 ] } },
{ "type": "Feature", "properties": { "DIRECCION": "Peaje de la Av. General Rumiñahui", "Codigo del cliente": "Peaje de la Av. General Rumiñahui" }, "geometry": { "type": "Point", "coordinates": [ -78.485332, -0.242651 ] } }
]
}
